[{"id": 1, "full_name": "Ali Valiyev", "username": "ali123", "password": "Ali@2024", "phone": "+998901234567", "balance": 1250000, "account_number": "8600123456789012", "status": "active"}, {"id": 2, "full_name": "Nodira Karimova", "username": "nodira", "password": "Nodira", "phone": "+998909876543", "balance": 850200, "account_number": "8600987612345678", "status": "active"}, {"id": 3, "full_name": "Javlonbek Xolmatov", "username": "javlon_x", "password": "Xolmatov2023", "phone": "+998931112233", "balance": 300000, "account_number": "9860123456123456", "status": "inactive"}, {"id": 4, "full_name": "Dilnoza Ergasheva", "username": "dilnoza.e", "password": "D1ln0za!", "phone": "+998935554433", "balance": 1200000, "account_number": "9860432198765432", "status": "active"}, {"id": 5, "full_name": "Shavkat Rasulov", "username": "shavkat_r", "password": "Sh@vk2024", "phone": "+998907654321", "balance": 540000, "account_number": "8600456789012345", "status": "blocked"}, {"id": 6, "full_name": "Gulbahor Abdullayeva", "username": "gulbahor_a", "password": "Gul12345", "phone": "+998933332211", "balance": 760000, "account_number": "9860123987654321", "status": "active"}, {"id": 7, "full_name": "Islomjon Qodirov", "username": "islom_q", "password": "Islom@2025", "phone": "+998901234890", "balance": 110000, "account_number": "8600678912345678", "status": "inactive"}, {"id": 8, "full_name": "Malika Saidova", "username": "malika.s", "password": "Mali2023!", "phone": "+998939998877", "balance": 920000, "account_number": "9860345678901234", "status": "active"}, {"id": 9, "full_name": "Bekzod Hamroyev", "username": "bekzod_h", "password": "Bekz0d123", "phone": "+998907712233", "balance": 480000, "account_number": "8600112233445566", "status": "active"}, {"id": 10, "full_name": "Ziyoda Olimova", "username": "ziyoda_o", "password": "Ziyoda@1", "phone": "+998934567890", "balance": 1500000, "account_number": "9860789012345678", "status": "active"}, {"username": "baxrombek", "password": "1234"}, {"username": "bax", "password": "1", "balanse": "100", "balance": 11}, {"username": "baxrom", "password": "1", "balanse": "1"}, {"username": "b", "password": "1", "balanse": "0"}]